sparse_dok/__init__.py
sparse_dok/__version__.py
sparse_dok/functions.py
sparse_dok/util.py
sparse_dok/components/__init__.py
sparse_dok/components/cuda_callable.py
sparse_dok/components/cuda_closed_hashmap.py
sparse_dok/components/sparse_dok_tensor.py
sparse_dok/components/cuda/__init__.py
sparse_dok/components/cuda/binary_search.cu
sparse_dok/components/cuda/bitonic.cu
sparse_dok/components/cuda/bmm_helpers.cu
sparse_dok/components/cuda/closed_hashmap_impl.cu
sparse_dok/components/cuda/closed_hashmap_impl.py
sparse_dok/components/cuda/closed_hashmap_impl_class.cu
sparse_dok/components/cuda/closed_hashmap_impl_preview.cu
sparse_dok/components/cuda/cuda_kernel.py
sparse_dok/components/cuda/filtered_elementwise.py
sparse_dok/components/cuda/hashmap.cu
sparse_dok/components/cuda/head.cu
sparse_dok/components/cuda/preview.cu
sparse_dok/components/cuda/reduce.cu
sparse_dok/components/cuda/safe_closed_hashmap_impl_class.cu
sparse_dok/components/cuda/smem_hashmap.cu
sparse_dok/components/cuda/smem_hashmap_simple.cu
sparse_dok/components/cuda/smem_tensor.cu
sparse_dok/components/cuda/sparse_dok_tensor_impl.cu
sparse_dok/components/cuda/sparse_dok_tensor_impl.py
sparse_dok/components/cuda/sparse_dok_tensor_impl_preview.cu
sparse_dok/components/cuda/stack.cu
sparse_dok/components/cuda/tensor_accessor.cu
sparse_dok/components/cuda/topkspspcsim.cu
sparse_dok/components/cuda/topkspspcsim.py
sparse_dok-0.1.9.4.dist-info/LICENCE
sparse_dok-0.1.9.4.dist-info/METADATA
sparse_dok-0.1.9.4.dist-info/WHEEL
sparse_dok-0.1.9.4.dist-info/top_level.txt
sparse_dok-0.1.9.4.dist-info/RECORD
