Metadata-Version: 2.1
Name: sparse-dok
Version: 0.1.9.4
Summary: sparse dok tensor implementation
Home-page: https://github.com/DeMoriarty/SparseDOK
Download-URL: https://github.com/DeMoriarty/SparseDOK/archive/v_0194.tar.gz
Author: demoriarty
Author-email: sahbanjan@gmail.com
License: MIT
Keywords: pytorch,sparse
Classifier: Development Status :: 3 - Alpha
Classifier: Intended Audience :: Developers
Classifier: Topic :: Software Development :: Build Tools
Classifier: License :: OSI Approved :: MIT License
Classifier: Programming Language :: Python :: 3
Classifier: Programming Language :: Python :: 3.4
Classifier: Programming Language :: Python :: 3.5
Classifier: Programming Language :: Python :: 3.6
Classifier: Programming Language :: Python :: 3.7
Classifier: Programming Language :: Python :: 3.8
Classifier: Programming Language :: Python :: 3.9
Classifier: Programming Language :: Python :: 3.10
License-File: LICENCE
Requires-Dist: numpy
Requires-Dist: torch (>=1.10.0)
Requires-Dist: sympy
